{
    "id": 26823,
    "game_number": "7",
    "start_time": "12:20",
    "actual_start_time": null,
    "date": "2022-04-30",
    "game_day": {
        "game_day_number": 11,
        "title": "11. Spieltag"
    },
    "game_status": null,
    "ingame_status": null,
    "audience": 15,
    "home_team_name": "Floorball Tigers Magdeburg II",
    "guest_team_name": "Floorball Pinguine Jena",
    "home_team_id": 5009,
    "guest_team_id": 5005,
    "home_team_logo": "/api/storage/blobs/redirect/eyJfcmFpbHMiOnsibWVzc2FnZSI6IkJBaHBHdz09IiwiZXhwIjpudWxsLCJwdXIiOiJibG9iX2lkIn19--63497b642f1fde98b6bc660bcdeae02221648f98/25-magdeburg.png",
    "home_team_small_logo": "/api/storage/blobs/redirect/eyJfcmFpbHMiOnsibWVzc2FnZSI6IkJBaHBHdz09IiwiZXhwIjpudWxsLCJwdXIiOiJibG9iX2lkIn19--63497b642f1fde98b6bc660bcdeae02221648f98/25-magdeburg.png",
    "guest_team_logo": "/api/storage/blobs/redirect/eyJfcmFpbHMiOnsibWVzc2FnZSI6IkJBaHBBYkk9IiwiZXhwIjpudWxsLCJwdXIiOiJibG9iX2lkIn19--95089c9f6090dfa928fec6dd0c1f6b832f9fc09d/117-jena.png",
    "guest_team_small_logo": "/api/storage/blobs/redirect/eyJfcmFpbHMiOnsibWVzc2FnZSI6IkJBaHBBYkk9IiwiZXhwIjpudWxsLCJwdXIiOiJibG9iX2lkIn19--95089c9f6090dfa928fec6dd0c1f6b832f9fc09d/117-jena.png",
    "live_stream_link": null,
    "vod_link": null,
    "events": [
        {
            "event_id": null,
            "event_type": "penalty",
            "event_team": "home",
            "period": 1,
            "home_goals": 0,
            "guest_goals": 0,
            "time": "2:57",
            "sortkey": "1-02:57",
            "number": 13,
            "penalty_type": "penalty_2",
            "penalty_type_string": "2'",
            "penalty_reason": 901,
            "penalty_reason_string": "Stockschlag"
        },
        {
            "event_id": null,
            "event_type": "goal",
            "event_team": "guest",
            "period": 1,
            "home_goals": 0,
            "guest_goals": 1,
            "time": "4:01",
            "sortkey": "1-04:01",
            "number": 23,
            "assist": 46,
            "goal_type": "regular",
            "goal_type_string": "Tor"
        },
        {
            "event_id": null,
            "event_type": "goal",
            "event_team": "guest",
            "period": 1,
            "home_goals": 0,
            "guest_goals": 2,
            "time": "7:45",
            "sortkey": "1-07:45",
            "number": 23,
            "assist": 2,
            "goal_type": "regular",
            "goal_type_string": "Tor"
        },
        {
            "event_id": null,
            "event_type": "goal",
            "event_team": "guest",
            "period": 1,
            "home_goals": 0,
            "guest_goals": 3,
            "time": "8:15",
            "sortkey": "1-08:15",
            "number": 19,
            "goal_type": "regular",
            "goal_type_string": "Tor"
        },
        {
            "event_id": 9001,
            "event_type": "timeout",
            "event_team": "home",
            "period": 1,
            "time": "8:15",
            "sortkey": "1-08:15"
        },
        {
            "event_id": null,
            "event_type": "goal",
            "event_team": "guest",
            "period": 2,
            "home_goals": 0,
            "guest_goals": 4,
            "time": "3:10",
            "sortkey": "2-03:10",
            "number": 23,
            "goal_type": "regular",
            "goal_type_string": "Tor"
        },
        {
            "event_id": null,
            "event_type": "goal",
            "event_team": "home",
            "period": 2,
            "home_goals": 1,
            "guest_goals": 4,
            "time": "3:44",
            "sortkey": "2-03:44",
            "number": 22,
            "goal_type": "regular",
            "goal_type_string": "Tor"
        },
        {
            "event_id": null,
            "event_type": "goal",
            "event_team": "guest",
            "period": 2,
            "home_goals": 1,
            "guest_goals": 5,
            "time": "6:31",
            "sortkey": "2-06:31",
            "number": 2,
            "goal_type": "regular",
            "goal_type_string": "Tor"
        },
        {
            "event_id": null,
            "event_type": "goal",
            "event_team": "home",
            "period": 2,
            "home_goals": 2,
            "guest_goals": 5,
            "time": "9:25",
            "sortkey": "2-09:25",
            "number": 21,
            "assist": 6,
            "goal_type": "regular",
            "goal_type_string": "Tor"
        }
    ],
    "players": {
        "home": [
            {
                "player_id": 19648,
                "goalkeeper": true,
                "player_name": "Grutman",
                "trikot_number": 1,
                "player_firstname": "Kateryna",
                "position": "Tor"
            },
            {
                "player_id": 21885,
                "player_name": "Käbel",
                "trikot_number": 6,
                "player_firstname": "Emma",
                "position": "Feld"
            },
            {
                "captain": true,
                "player_id": 21954,
                "player_name": "Handl",
                "trikot_number": 10,
                "player_firstname": "Marius - Damian",
                "position": "Feld"
            },
            {
                "player_id": 21939,
                "player_name": "Goihl",
                "trikot_number": 11,
                "player_firstname": "Katharina",
                "position": "Feld"
            },
            {
                "player_id": 19647,
                "player_name": "Aghasarshar",
                "trikot_number": 13,
                "player_firstname": "Delaram",
                "position": "Feld"
            },
            {
                "player_id": 21938,
                "player_name": "Wegener",
                "trikot_number": 16,
                "player_firstname": "Leonie Ciara",
                "position": "Feld"
            },
            {
                "player_id": 21884,
                "player_name": "Selimaj",
                "trikot_number": 21,
                "player_firstname": "Aliya",
                "position": "Feld"
            },
            {
                "player_id": 21941,
                "player_name": "Grassel",
                "trikot_number": 22,
                "player_firstname": "Vanessa",
                "position": "Feld"
            }
        ],
        "guest": [
            {
                "player_id": 21961,
                "goalkeeper": true,
                "player_name": "Schindler",
                "trikot_number": 46,
                "player_firstname": "Anton",
                "position": "Tor"
            },
            {
                "captain": true,
                "player_id": 20480,
                "player_name": "Siemers",
                "trikot_number": 2,
                "player_firstname": "Jarne",
                "position": "Feld"
            },
            {
                "player_id": 21964,
                "player_name": "Thoms",
                "trikot_number": 20,
                "player_firstname": "Felix",
                "position": "Feld"
            },
            {
                "player_id": 21956,
                "player_name": "Oehrlich",
                "trikot_number": 23,
                "player_firstname": "Leopold",
                "position": "Feld"
            },
            {
                "player_id": 22379,
                "player_name": "Stadeler",
                "trikot_number": 39,
                "player_firstname": "Theodor",
                "position": "Feld"
            },
            {
                "player_id": 21957,
                "player_name": "Grüner",
                "trikot_number": 30,
                "player_firstname": "Maximilian Carl Ulrich",
                "position": "Feld"
            },
            {
                "player_id": 19522,
                "player_name": "Braun",
                "trikot_number": 54,
                "player_firstname": "Marie",
                "position": "Feld"
            },
            {
                "player_id": 21960,
                "player_name": "Richtsteiger",
                "trikot_number": 77,
                "player_firstname": "Marie",
                "position": "Feld"
            },
            {
                "player_id": 21963,
                "player_name": "Truhm",
                "trikot_number": 5,
                "player_firstname": "Charlotte",
                "position": "Feld"
            },
            {
                "player_id": 21958,
                "player_name": "Conrad",
                "trikot_number": 19,
                "player_firstname": "Kurt",
                "position": "Feld"
            }
        ]
    },
    "started": true,
    "ended": true,
    "result_string": "2:5",
    "result": {
        "home_goals": 2,
        "guest_goals": 5,
        "home_goals_period": [
            0,
            2,
            0,
            0
        ],
        "guest_goals_period": [
            3,
            2,
            0,
            0
        ],
        "postfix": {
            "short": "",
            "long": ""
        },
        "forfait": false,
        "overtime": false
    },
    "league_id": 1152,
    "league_name": "Platzierungsrunde Ost U11 Junioren Kleinfeld",
    "league_short_name": "PRU11",
    "game_operation_id": 6,
    "game_operation_name": "SBK Ost",
    "game_operation_short_name": "SBK Ost",
    "game_operation_slug": "SBK Ost",
    "period_titles": [
        {
            "period": 1,
            "short_title": "1",
            "title": "1. Hälfte",
            "status_id": "period1",
            "can_end_game": false,
            "optional": false,
            "running": true
        },
        {
            "period": 1.5,
            "short_title": "HZ",
            "title": "Halbzeitpause",
            "status_id": "pause1",
            "can_end_game": false,
            "optional": false,
            "running": false
        },
        {
            "period": 2,
            "short_title": "2",
            "title": "2. Hälfte",
            "status_id": "period2",
            "can_end_game": true,
            "optional": false,
            "running": true
        },
        {
            "period": 2.5,
            "short_title": "PV",
            "title": "Pause vor Verlängerung",
            "status_id": "pause_et",
            "can_end_game": false,
            "optional": true,
            "running": false
        },
        {
            "period": 3,
            "short_title": "V",
            "title": "Verlängerung",
            "status_id": "extratime",
            "can_end_game": true,
            "optional": true,
            "running": true
        },
        {
            "period": 4.5,
            "short_title": "PP",
            "title": "Pause vor Penalty-Schießen",
            "status_id": "pause_ps",
            "can_end_game": false,
            "optional": true,
            "running": false
        },
        {
            "period": 4,
            "short_title": "P",
            "title": "Penalty-Schießen",
            "status_id": "penalty_shots",
            "can_end_game": true,
            "optional": true,
            "running": true
        }
    ],
    "current_period_title": null,
    "arena": 234,
    "arena_name": "von-Siemens-Gymnasium",
    "arena_address": "Stendaler Straße 10, 39106 Magdeburg",
    "arena_short": "Magdeburg, von-Siemens-Gymnasium",
    "nominated_referees": "Ausrichter",
    "deletable": false,
    "notice_type": null,
    "notice_string": null,
    "referees": [
        {
            "license_id": "540",
            "first_name": "Christian",
            "last_name": "Hoffmann"
        },
        {
            "license_id": "1792",
            "first_name": "Benjamin",
            "last_name": "Ehrhardt"
        }
    ]
}