{
    "id": 290,
    "game_number": "16",
    "start_time": "18:45",
    "actual_start_time": null,
    "date": "2014-11-09",
    "game_day": {
        "game_day_number": 2,
        "title": "2. Spieltag"
    },
    "game_status": null,
    "ingame_status": null,
    "audience": 16,
    "home_team_name": "SSF Dragons Bonn",
    "guest_team_name": "TB Burgsteinfurt 1862 e.V.",
    "home_team_id": 973,
    "guest_team_id": 1558,
    "home_team_logo": "/api/storage/blobs/redirect/eyJfcmFpbHMiOnsibWVzc2FnZSI6IkJBaHBBaTBCIiwiZXhwIjpudWxsLCJwdXIiOiJibG9iX2lkIn19--cd3f73b1aba43dcac5e3ef385cbe41860cfe1c8b/168.png",
    "home_team_small_logo": "/api/storage/blobs/redirect/eyJfcmFpbHMiOnsibWVzc2FnZSI6IkJBaHBBaTBCIiwiZXhwIjpudWxsLCJwdXIiOiJibG9iX2lkIn19--cd3f73b1aba43dcac5e3ef385cbe41860cfe1c8b/168.png",
    "guest_team_logo": "/api/storage/blobs/redirect/eyJfcmFpbHMiOnsibWVzc2FnZSI6IkJBaHBlZz09IiwiZXhwIjpudWxsLCJwdXIiOiJibG9iX2lkIn19--2fb5379631218a25792eead34972649364a7977b/155-tbburgsteinfurt.png",
    "guest_team_small_logo": "/api/storage/blobs/redirect/eyJfcmFpbHMiOnsibWVzc2FnZSI6IkJBaHBlZz09IiwiZXhwIjpudWxsLCJwdXIiOiJibG9iX2lkIn19--2fb5379631218a25792eead34972649364a7977b/155-tbburgsteinfurt.png",
    "live_stream_link": null,
    "vod_link": null,
    "events": [
        {
            "event_id": null,
            "event_type": "goal",
            "event_team": "home",
            "period": 1,
            "home_goals": 1,
            "guest_goals": null,
            "time": "2:34",
            "sortkey": "1-02:34",
            "number": 9,
            "assist": 10,
            "goal_type": "regular",
            "goal_type_string": "Tor"
        },
        {
            "event_id": null,
            "event_type": "goal",
            "event_team": "guest",
            "period": 1,
            "home_goals": 1,
            "guest_goals": 1,
            "time": "8:21",
            "sortkey": "1-08:21",
            "number": 26,
            "goal_type": "regular",
            "goal_type_string": "Tor"
        },
        {
            "event_id": null,
            "event_type": "goal",
            "event_team": "home",
            "period": 1,
            "home_goals": 2,
            "guest_goals": 1,
            "time": "14:03",
            "sortkey": "1-14:03",
            "number": 4,
            "assist": 7,
            "goal_type": "regular",
            "goal_type_string": "Tor"
        },
        {
            "event_id": null,
            "event_type": "goal",
            "event_team": "guest",
            "period": 1,
            "home_goals": 2,
            "guest_goals": 2,
            "time": "15:04",
            "sortkey": "1-15:04",
            "number": 6,
            "goal_type": "regular",
            "goal_type_string": "Tor"
        },
        {
            "event_id": null,
            "event_type": "goal",
            "event_team": "guest",
            "period": 1,
            "home_goals": 2,
            "guest_goals": 3,
            "time": "16:49",
            "sortkey": "1-16:49",
            "number": 27,
            "goal_type": "regular",
            "goal_type_string": "Tor"
        },
        {
            "event_id": null,
            "event_type": "penalty",
            "event_team": "home",
            "period": 1,
            "home_goals": 2,
            "guest_goals": 3,
            "time": "19:23",
            "sortkey": "1-19:23",
            "number": 4,
            "penalty_type": "penalty_2",
            "penalty_type_string": "2'",
            "penalty_reason": 904,
            "penalty_reason_string": "Hoher Stock"
        },
        {
            "event_id": null,
            "event_type": "goal",
            "event_team": "home",
            "period": 2,
            "home_goals": 3,
            "guest_goals": 3,
            "time": "0:52",
            "sortkey": "2-00:52",
            "number": 7,
            "goal_type": "regular",
            "goal_type_string": "Tor"
        },
        {
            "event_id": null,
            "event_type": "goal",
            "event_team": "home",
            "period": 2,
            "home_goals": 4,
            "guest_goals": 3,
            "time": "2:47",
            "sortkey": "2-02:47",
            "number": 5,
            "assist": 6,
            "goal_type": "regular",
            "goal_type_string": "Tor"
        },
        {
            "event_id": null,
            "event_type": "goal",
            "event_team": "home",
            "period": 2,
            "home_goals": 5,
            "guest_goals": 3,
            "time": "5:22",
            "sortkey": "2-05:22",
            "number": 6,
            "assist": 8,
            "goal_type": "regular",
            "goal_type_string": "Tor"
        },
        {
            "event_id": null,
            "event_type": "goal",
            "event_team": "guest",
            "period": 2,
            "home_goals": 5,
            "guest_goals": 4,
            "time": "5:26",
            "sortkey": "2-05:26",
            "number": 26,
            "goal_type": "regular",
            "goal_type_string": "Tor"
        },
        {
            "event_id": null,
            "event_type": "goal",
            "event_team": "home",
            "period": 2,
            "home_goals": 6,
            "guest_goals": 4,
            "time": "7:25",
            "sortkey": "2-07:25",
            "number": 5,
            "goal_type": "regular",
            "goal_type_string": "Tor"
        },
        {
            "event_id": null,
            "event_type": "goal",
            "event_team": "home",
            "period": 2,
            "home_goals": 7,
            "guest_goals": 4,
            "time": "7:40",
            "sortkey": "2-07:40",
            "number": 6,
            "goal_type": "regular",
            "goal_type_string": "Tor"
        },
        {
            "event_id": null,
            "event_type": "goal",
            "event_team": "guest",
            "period": 2,
            "home_goals": 7,
            "guest_goals": 5,
            "time": "9:32",
            "sortkey": "2-09:32",
            "number": 26,
            "goal_type": "regular",
            "goal_type_string": "Tor"
        },
        {
            "event_id": null,
            "event_type": "goal",
            "event_team": "guest",
            "period": 2,
            "home_goals": 7,
            "guest_goals": 6,
            "time": "9:36",
            "sortkey": "2-09:36",
            "number": 26,
            "goal_type": "regular",
            "goal_type_string": "Tor"
        },
        {
            "event_id": null,
            "event_type": "goal",
            "event_team": "home",
            "period": 2,
            "home_goals": 8,
            "guest_goals": 6,
            "time": "15:07",
            "sortkey": "2-15:07",
            "number": 16,
            "goal_type": "regular",
            "goal_type_string": "Tor"
        },
        {
            "event_id": 9002,
            "event_type": "timeout",
            "event_team": "guest",
            "period": 2,
            "time": "15:07",
            "sortkey": "2-15:07"
        },
        {
            "event_id": null,
            "event_type": "penalty",
            "event_team": "home",
            "period": 2,
            "home_goals": 8,
            "guest_goals": 6,
            "time": "18:00",
            "sortkey": "2-18:00",
            "number": 16,
            "penalty_type": "penalty_2",
            "penalty_type_string": "2'",
            "penalty_reason": 925,
            "penalty_reason_string": "Reklamieren"
        },
        {
            "event_id": null,
            "event_type": "penalty",
            "event_team": "guest",
            "period": 2,
            "home_goals": 8,
            "guest_goals": 6,
            "time": "18:00",
            "sortkey": "2-18:00",
            "number": 26,
            "penalty_type": "penalty_2",
            "penalty_type_string": "2'",
            "penalty_reason": 907,
            "penalty_reason_string": "Stoßen"
        }
    ],
    "players": {
        "home": [
            {
                "player_id": 6188,
                "player_name": "Deniz",
                "trikot_number": 16,
                "player_firstname": "Semih",
                "position": "Feld"
            },
            {
                "player_id": 2604,
                "player_name": "de Lamboy",
                "trikot_number": 14,
                "player_firstname": "Florian",
                "position": "Feld"
            },
            {
                "player_id": 2998,
                "player_name": "Giesecke",
                "trikot_number": 12,
                "player_firstname": "Maximilian",
                "position": "Feld"
            },
            {
                "player_id": 5214,
                "player_name": "Braun",
                "trikot_number": 11,
                "player_firstname": "Till",
                "position": "Feld"
            },
            {
                "player_id": 1027,
                "player_name": "Jacome",
                "trikot_number": 10,
                "player_firstname": "Elena",
                "position": "Feld"
            },
            {
                "captain": true,
                "player_id": 1741,
                "player_name": "Jahn",
                "trikot_number": 9,
                "player_firstname": "Tim",
                "position": "Feld"
            },
            {
                "player_id": 3008,
                "player_name": "Peschke",
                "trikot_number": 8,
                "player_firstname": "Raphael",
                "position": "Feld"
            },
            {
                "player_id": 14549,
                "player_name": "Heinen",
                "trikot_number": 7,
                "player_firstname": "Jannik",
                "position": "Feld"
            },
            {
                "player_id": 15235,
                "player_name": "Temel",
                "trikot_number": 6,
                "player_firstname": "Baris",
                "position": "Feld"
            },
            {
                "player_id": 10387,
                "player_name": "Temel",
                "trikot_number": 5,
                "player_firstname": "Safak",
                "position": "Feld"
            },
            {
                "player_id": 281,
                "player_name": "Dzubiel",
                "trikot_number": 4,
                "player_firstname": "Yinon ",
                "position": "Feld"
            },
            {
                "player_id": 10889,
                "goalkeeper": true,
                "player_name": "Wendeler",
                "trikot_number": 2,
                "player_firstname": "Dominik",
                "position": "Tor"
            },
            {
                "player_id": 12210,
                "goalkeeper": true,
                "player_name": "Aydin",
                "trikot_number": 1,
                "player_firstname": "Alihan",
                "position": "Tor"
            }
        ],
        "guest": [
            {
                "player_id": 10934,
                "player_name": "Deitert",
                "trikot_number": 19,
                "player_firstname": "Jannik",
                "position": "Feld"
            },
            {
                "player_id": 9095,
                "goalkeeper": true,
                "player_name": "Lehmann",
                "trikot_number": 12,
                "player_firstname": "Yanick",
                "position": "Tor"
            },
            {
                "player_id": 15385,
                "player_name": "Hallau",
                "trikot_number": 10,
                "player_firstname": "Kai",
                "position": "Feld"
            },
            {
                "player_id": 11872,
                "player_name": "Kauling",
                "trikot_number": 6,
                "player_firstname": "Lasse",
                "position": "Feld"
            },
            {
                "player_id": 5685,
                "goalkeeper": true,
                "player_name": "Wohlmeiner",
                "trikot_number": 1,
                "player_firstname": "Till",
                "position": "Tor"
            },
            {
                "player_id": 6601,
                "player_name": "Lamann",
                "trikot_number": 22,
                "player_firstname": "Thilo",
                "position": "Feld"
            },
            {
                "player_id": 7547,
                "player_name": "Karhof",
                "trikot_number": 24,
                "player_firstname": "Julian",
                "position": "Feld"
            },
            {
                "captain": true,
                "player_id": 1296,
                "player_name": "Bartsch",
                "trikot_number": 26,
                "player_firstname": "Marvin",
                "position": "Feld"
            },
            {
                "player_id": 10916,
                "player_name": "Brebaum",
                "trikot_number": 27,
                "player_firstname": "Jan Philip",
                "position": "Feld"
            }
        ]
    },
    "started": false,
    "ended": false,
    "result_string": "8:6",
    "result": {
        "home_goals": 8,
        "guest_goals": 6,
        "home_goals_period": [
            1,
            7,
            0,
            0
        ],
        "guest_goals_period": [
            0,
            6,
            0,
            0
        ],
        "postfix": {
            "short": "",
            "long": ""
        },
        "forfait": false,
        "overtime": false
    },
    "league_id": 410,
    "league_name": "Westliga Herren Kleinfeld U15",
    "league_short_name": "Westliga U15 KF",
    "game_operation_id": 10,
    "game_operation_name": "Nordrhein-Westfälischer Floorball Verband",
    "game_operation_short_name": "NWFV",
    "game_operation_slug": "NWFV",
    "period_titles": [
        {
            "period": 1,
            "short_title": "1",
            "title": "1. Hälfte",
            "status_id": "period1",
            "can_end_game": false,
            "optional": false,
            "running": true
        },
        {
            "period": 1.5,
            "short_title": "HZ",
            "title": "Halbzeitpause",
            "status_id": "pause1",
            "can_end_game": false,
            "optional": false,
            "running": false
        },
        {
            "period": 2,
            "short_title": "2",
            "title": "2. Hälfte",
            "status_id": "period2",
            "can_end_game": true,
            "optional": false,
            "running": true
        },
        {
            "period": 2.5,
            "short_title": "PV",
            "title": "Pause vor Verlängerung",
            "status_id": "pause_et",
            "can_end_game": false,
            "optional": true,
            "running": false
        },
        {
            "period": 3,
            "short_title": "V",
            "title": "Verlängerung",
            "status_id": "extratime",
            "can_end_game": true,
            "optional": true,
            "running": true
        },
        {
            "period": 4.5,
            "short_title": "PP",
            "title": "Pause vor Penalty-Schießen",
            "status_id": "pause_ps",
            "can_end_game": false,
            "optional": true,
            "running": false
        },
        {
            "period": 4,
            "short_title": "P",
            "title": "Penalty-Schießen",
            "status_id": "penalty_shots",
            "can_end_game": true,
            "optional": true,
            "running": true
        }
    ],
    "current_period_title": null,
    "arena": 232,
    "arena_name": "Hochdahl, Rankestraße",
    "arena_address": "Rankestraße 4-6, 40699 Erkrath",
    "arena_short": "Erkrath, Hochdahl, Rankestraße",
    "nominated_referees": "SSC Hochdahl",
    "deletable": true,
    "notice_type": null,
    "notice_string": null,
    "referees": []
}