{
    "id": 31120,
    "game_number": "37",
    "start_time": "14:00",
    "actual_start_time": "17:49",
    "date": "2023-11-18",
    "game_day": {
        "game_day_number": 4,
        "title": "4. Spieltag"
    },
    "game_status": "finalized",
    "ingame_status": "period2",
    "audience": 36,
    "home_team_name": "BW96 Schenefeld",
    "guest_team_name": "SG Bordesholm/Preetz",
    "home_team_id": 5687,
    "guest_team_id": 5693,
    "home_team_logo": "/api/storage/blobs/redirect/eyJfcmFpbHMiOnsibWVzc2FnZSI6IkJBaHBNdz09IiwiZXhwIjpudWxsLCJwdXIiOiJibG9iX2lkIn19--eb18cc21afc2e7d181f9f9e22c6a7ee1d739330f/68-schenefeld.png",
    "home_team_small_logo": "/api/storage/blobs/redirect/eyJfcmFpbHMiOnsibWVzc2FnZSI6IkJBaHBNdz09IiwiZXhwIjpudWxsLCJwdXIiOiJibG9iX2lkIn19--eb18cc21afc2e7d181f9f9e22c6a7ee1d739330f/68-schenefeld.png",
    "guest_team_logo": "/api/storage/blobs/redirect/eyJfcmFpbHMiOnsibWVzc2FnZSI6IkJBaHBidz09IiwiZXhwIjpudWxsLCJwdXIiOiJibG9iX2lkIn19--ccd1335951601be5acf9fced95c90aee9cc889d6/159-bordesholm.png",
    "guest_team_small_logo": "/api/storage/blobs/redirect/eyJfcmFpbHMiOnsibWVzc2FnZSI6IkJBaHBidz09IiwiZXhwIjpudWxsLCJwdXIiOiJibG9iX2lkIn19--ccd1335951601be5acf9fced95c90aee9cc889d6/159-bordesholm.png",
    "live_stream_link": null,
    "vod_link": null,
    "events": [
        {
            "event_id": 1,
            "event_type": "goal",
            "event_team": "home",
            "period": 1,
            "home_goals": 1,
            "guest_goals": 0,
            "time": "1:40",
            "sortkey": "1-01:40",
            "number": 5,
            "assist": 0,
            "goal_type": "regular",
            "goal_type_string": "Tor"
        },
        {
            "event_id": 2,
            "event_type": "goal",
            "event_team": "home",
            "period": 1,
            "home_goals": 2,
            "guest_goals": 0,
            "time": "2:16",
            "sortkey": "1-02:16",
            "number": 37,
            "assist": 0,
            "goal_type": "regular",
            "goal_type_string": "Tor"
        },
        {
            "event_id": 3,
            "event_type": "goal",
            "event_team": "home",
            "period": 1,
            "home_goals": 3,
            "guest_goals": 0,
            "time": "4:07",
            "sortkey": "1-04:07",
            "number": 19,
            "assist": 5,
            "goal_type": "regular",
            "goal_type_string": "Tor"
        },
        {
            "event_id": 4,
            "event_type": "goal",
            "event_team": "home",
            "period": 1,
            "home_goals": 4,
            "guest_goals": 0,
            "time": "4:47",
            "sortkey": "1-04:47",
            "number": 14,
            "assist": 0,
            "goal_type": "regular",
            "goal_type_string": "Tor"
        },
        {
            "event_id": 5,
            "event_type": "goal",
            "event_team": "home",
            "period": 1,
            "home_goals": 5,
            "guest_goals": 0,
            "time": "4:52",
            "sortkey": "1-04:52",
            "number": 19,
            "assist": 5,
            "goal_type": "regular",
            "goal_type_string": "Tor"
        },
        {
            "event_id": 6,
            "event_type": "goal",
            "event_team": "guest",
            "period": 1,
            "home_goals": 5,
            "guest_goals": 1,
            "time": "5:04",
            "sortkey": "1-05:04",
            "number": 20,
            "assist": 0,
            "goal_type": "regular",
            "goal_type_string": "Tor"
        },
        {
            "event_id": 7,
            "event_type": "goal",
            "event_team": "home",
            "period": 1,
            "home_goals": 6,
            "guest_goals": 1,
            "time": "9:06",
            "sortkey": "1-09:06",
            "number": 16,
            "assist": 14,
            "goal_type": "regular",
            "goal_type_string": "Tor"
        },
        {
            "event_id": 8,
            "event_type": "goal",
            "event_team": "home",
            "period": 1,
            "home_goals": 7,
            "guest_goals": 1,
            "time": "13:12",
            "sortkey": "1-13:12",
            "number": 19,
            "assist": 5,
            "goal_type": "regular",
            "goal_type_string": "Tor"
        },
        {
            "event_id": 9,
            "event_type": "goal",
            "event_team": "home",
            "period": 1,
            "home_goals": 8,
            "guest_goals": 1,
            "time": "13:34",
            "sortkey": "1-13:34",
            "number": 19,
            "assist": 0,
            "goal_type": "regular",
            "goal_type_string": "Tor"
        },
        {
            "event_id": 10,
            "event_type": "goal",
            "event_team": "home",
            "period": 1,
            "home_goals": 9,
            "guest_goals": 1,
            "time": "15:54",
            "sortkey": "1-15:54",
            "number": 5,
            "assist": 29,
            "goal_type": "regular",
            "goal_type_string": "Tor"
        },
        {
            "event_id": 11,
            "event_type": "goal",
            "event_team": "home",
            "period": 1,
            "home_goals": 10,
            "guest_goals": 1,
            "time": "15:59",
            "sortkey": "1-15:59",
            "number": 19,
            "assist": 0,
            "goal_type": "regular",
            "goal_type_string": "Tor"
        },
        {
            "event_id": 12,
            "event_type": "goal",
            "event_team": "home",
            "period": 1,
            "home_goals": 11,
            "guest_goals": 1,
            "time": "16:23",
            "sortkey": "1-16:23",
            "number": 16,
            "assist": 14,
            "goal_type": "regular",
            "goal_type_string": "Tor"
        },
        {
            "event_id": 13,
            "event_type": "goal",
            "event_team": "home",
            "period": 1,
            "home_goals": 12,
            "guest_goals": 1,
            "time": "18:56",
            "sortkey": "1-18:56",
            "number": 5,
            "assist": 19,
            "goal_type": "regular",
            "goal_type_string": "Tor"
        },
        {
            "event_id": 14,
            "event_type": "goal",
            "event_team": "home",
            "period": 2,
            "home_goals": 13,
            "guest_goals": 1,
            "time": "0:49",
            "sortkey": "2-00:49",
            "number": 37,
            "assist": 0,
            "goal_type": "regular",
            "goal_type_string": "Tor"
        },
        {
            "event_id": 15,
            "event_type": "goal",
            "event_team": "home",
            "period": 2,
            "home_goals": 14,
            "guest_goals": 1,
            "time": "1:34",
            "sortkey": "2-01:34",
            "number": 19,
            "assist": 5,
            "goal_type": "regular",
            "goal_type_string": "Tor"
        },
        {
            "event_id": 16,
            "event_type": "goal",
            "event_team": "home",
            "period": 2,
            "home_goals": 15,
            "guest_goals": 1,
            "time": "2:50",
            "sortkey": "2-02:50",
            "number": 5,
            "assist": 19,
            "goal_type": "regular",
            "goal_type_string": "Tor"
        },
        {
            "event_id": 17,
            "event_type": "goal",
            "event_team": "home",
            "period": 2,
            "home_goals": 16,
            "guest_goals": 1,
            "time": "4:52",
            "sortkey": "2-04:52",
            "number": 5,
            "assist": 19,
            "goal_type": "regular",
            "goal_type_string": "Tor"
        },
        {
            "event_id": 18,
            "event_type": "goal",
            "event_team": "home",
            "period": 2,
            "home_goals": 17,
            "guest_goals": 1,
            "time": "5:00",
            "sortkey": "2-05:00",
            "number": 5,
            "assist": 0,
            "goal_type": "regular",
            "goal_type_string": "Tor"
        },
        {
            "event_id": 19,
            "event_type": "goal",
            "event_team": "home",
            "period": 2,
            "home_goals": 18,
            "guest_goals": 1,
            "time": "5:24",
            "sortkey": "2-05:24",
            "number": 5,
            "assist": 0,
            "goal_type": "regular",
            "goal_type_string": "Tor"
        },
        {
            "event_id": 20,
            "event_type": "goal",
            "event_team": "guest",
            "period": 2,
            "home_goals": 18,
            "guest_goals": 2,
            "time": "8:31",
            "sortkey": "2-08:31",
            "number": 12,
            "assist": 0,
            "goal_type": "regular",
            "goal_type_string": "Tor"
        },
        {
            "event_id": 21,
            "event_type": "goal",
            "event_team": "home",
            "period": 2,
            "home_goals": 19,
            "guest_goals": 2,
            "time": "10:01",
            "sortkey": "2-10:01",
            "number": 5,
            "assist": 19,
            "goal_type": "regular",
            "goal_type_string": "Tor"
        },
        {
            "event_id": 22,
            "event_type": "goal",
            "event_team": "home",
            "period": 2,
            "home_goals": 20,
            "guest_goals": 2,
            "time": "10:32",
            "sortkey": "2-10:32",
            "number": 19,
            "assist": 29,
            "goal_type": "regular",
            "goal_type_string": "Tor"
        },
        {
            "event_id": 23,
            "event_type": "goal",
            "event_team": "guest",
            "period": 2,
            "home_goals": 20,
            "guest_goals": 3,
            "time": "12:47",
            "sortkey": "2-12:47",
            "number": 20,
            "assist": 0,
            "goal_type": "regular",
            "goal_type_string": "Tor"
        },
        {
            "event_id": 24,
            "event_type": "goal",
            "event_team": "home",
            "period": 2,
            "home_goals": 21,
            "guest_goals": 3,
            "time": "13:06",
            "sortkey": "2-13:06",
            "number": 29,
            "assist": 0,
            "goal_type": "regular",
            "goal_type_string": "Tor"
        },
        {
            "event_id": 25,
            "event_type": "goal",
            "event_team": "home",
            "period": 2,
            "home_goals": 22,
            "guest_goals": 3,
            "time": "13:09",
            "sortkey": "2-13:09",
            "number": 5,
            "assist": 0,
            "goal_type": "regular",
            "goal_type_string": "Tor"
        },
        {
            "event_id": 26,
            "event_type": "goal",
            "event_team": "guest",
            "period": 2,
            "home_goals": 22,
            "guest_goals": 4,
            "time": "14:12",
            "sortkey": "2-14:12",
            "number": 12,
            "assist": 0,
            "goal_type": "regular",
            "goal_type_string": "Tor"
        },
        {
            "event_id": 27,
            "event_type": "goal",
            "event_team": "home",
            "period": 2,
            "home_goals": 23,
            "guest_goals": 4,
            "time": "14:23",
            "sortkey": "2-14:23",
            "number": 5,
            "assist": 19,
            "goal_type": "regular",
            "goal_type_string": "Tor"
        },
        {
            "event_id": 28,
            "event_type": "goal",
            "event_team": "home",
            "period": 2,
            "home_goals": 24,
            "guest_goals": 4,
            "time": "14:36",
            "sortkey": "2-14:36",
            "number": 19,
            "assist": 5,
            "goal_type": "regular",
            "goal_type_string": "Tor"
        },
        {
            "event_id": 29,
            "event_type": "goal",
            "event_team": "home",
            "period": 2,
            "home_goals": 25,
            "guest_goals": 4,
            "time": "15:35",
            "sortkey": "2-15:35",
            "number": 19,
            "assist": 0,
            "goal_type": "regular",
            "goal_type_string": "Tor"
        },
        {
            "event_id": 30,
            "event_type": "goal",
            "event_team": "guest",
            "period": 2,
            "home_goals": 25,
            "guest_goals": 5,
            "time": "17:16",
            "sortkey": "2-17:16",
            "number": 21,
            "assist": 0,
            "goal_type": "regular",
            "goal_type_string": "Tor"
        },
        {
            "event_id": 31,
            "event_type": "goal",
            "event_team": "home",
            "period": 2,
            "home_goals": 26,
            "guest_goals": 5,
            "time": "17:26",
            "sortkey": "2-17:26",
            "number": 19,
            "assist": 0,
            "goal_type": "regular",
            "goal_type_string": "Tor"
        },
        {
            "event_id": 32,
            "event_type": "goal",
            "event_team": "home",
            "period": 2,
            "home_goals": 27,
            "guest_goals": 5,
            "time": "19:24",
            "sortkey": "2-19:24",
            "number": 19,
            "assist": 5,
            "goal_type": "regular",
            "goal_type_string": "Tor"
        }
    ],
    "players": {
        "home": [
            {
                "player_id": 24754,
                "goalkeeper": true,
                "player_name": "Eggerstedt",
                "trikot_number": 1,
                "player_firstname": "Jarik",
                "position": "Tor"
            },
            {
                "captain": true,
                "player_id": 21206,
                "player_name": "Löw",
                "trikot_number": 5,
                "player_firstname": "Filip",
                "position": "Feld"
            },
            {
                "player_id": 24302,
                "player_name": "Jürgens",
                "trikot_number": 19,
                "player_firstname": "Mika",
                "position": "Feld"
            },
            {
                "player_id": 22483,
                "player_name": "de Temple",
                "trikot_number": 14,
                "player_firstname": "Rudi",
                "position": "Feld"
            },
            {
                "player_id": 24111,
                "player_name": "Arabaci",
                "trikot_number": 36,
                "player_firstname": "Hamdi Sami",
                "position": "Feld"
            },
            {
                "player_id": 24279,
                "player_name": "Andersen",
                "trikot_number": 29,
                "player_firstname": "Ryan",
                "position": "Feld"
            },
            {
                "player_id": 21210,
                "player_name": "Rahm",
                "trikot_number": 37,
                "player_firstname": "Felix",
                "position": "Feld"
            },
            {
                "player_id": 24110,
                "player_name": "Bröder",
                "trikot_number": 16,
                "player_firstname": "Paul",
                "position": "Feld"
            }
        ],
        "guest": [
            {
                "player_id": 24146,
                "goalkeeper": true,
                "player_name": "Laupichler",
                "trikot_number": 14,
                "player_firstname": "Julia Malina ",
                "position": "Tor"
            },
            {
                "captain": true,
                "player_id": 24139,
                "player_name": "Witt",
                "trikot_number": 11,
                "player_firstname": "Jonas",
                "position": "Feld"
            },
            {
                "player_id": 24142,
                "player_name": "Kabon",
                "trikot_number": 24,
                "player_firstname": "Jonas",
                "position": "Feld"
            },
            {
                "player_id": 24147,
                "player_name": "Lehner",
                "trikot_number": 13,
                "player_firstname": "Anton Felix",
                "position": "Feld"
            },
            {
                "player_id": 24292,
                "player_name": "Schick",
                "trikot_number": 21,
                "player_firstname": "Mattis",
                "position": "Feld"
            },
            {
                "player_id": 20296,
                "player_name": "Hannich",
                "trikot_number": 27,
                "player_firstname": "Bosse",
                "position": "Feld"
            },
            {
                "player_id": 20295,
                "player_name": "Hannich",
                "trikot_number": 20,
                "player_firstname": "Greta",
                "position": "Feld"
            },
            {
                "player_id": 18658,
                "player_name": "Nielson",
                "trikot_number": 12,
                "player_firstname": "Greta",
                "position": "Feld"
            },
            {
                "player_id": 24354,
                "player_name": "Wenglewski",
                "trikot_number": 23,
                "player_firstname": "Ben",
                "position": "Feld"
            }
        ]
    },
    "started": true,
    "ended": true,
    "result_string": "27:5",
    "result": {
        "home_goals": 27,
        "guest_goals": 5,
        "home_goals_period": [
            12,
            15,
            0,
            0
        ],
        "guest_goals_period": [
            1,
            4,
            0,
            0
        ],
        "postfix": {
            "short": "",
            "long": ""
        },
        "forfait": false,
        "overtime": false
    },
    "league_id": 1378,
    "league_name": "U13 KF Regionalliga Nord",
    "league_short_name": "U13 KF",
    "game_operation_id": 5,
    "game_operation_name": "Floorballverband Schleswig-Holstein",
    "game_operation_short_name": "FLV-SH",
    "game_operation_slug": "FLV-SH",
    "period_titles": [
        {
            "period": 1,
            "short_title": "1",
            "title": "1. Hälfte",
            "status_id": "period1",
            "can_end_game": false,
            "optional": false,
            "running": true
        },
        {
            "period": 1.5,
            "short_title": "HZ",
            "title": "Halbzeitpause",
            "status_id": "pause1",
            "can_end_game": false,
            "optional": false,
            "running": false
        },
        {
            "period": 2,
            "short_title": "2",
            "title": "2. Hälfte",
            "status_id": "period2",
            "can_end_game": true,
            "optional": false,
            "running": true
        },
        {
            "period": 2.5,
            "short_title": "PV",
            "title": "Pause vor Verlängerung",
            "status_id": "pause_et",
            "can_end_game": false,
            "optional": true,
            "running": false
        },
        {
            "period": 3,
            "short_title": "V",
            "title": "Verlängerung",
            "status_id": "extratime",
            "can_end_game": true,
            "optional": true,
            "running": true
        },
        {
            "period": 4.5,
            "short_title": "PP",
            "title": "Pause vor Penalty-Schießen",
            "status_id": "pause_ps",
            "can_end_game": false,
            "optional": true,
            "running": false
        },
        {
            "period": 4,
            "short_title": "P",
            "title": "Penalty-Schießen",
            "status_id": "penalty_shots",
            "can_end_game": true,
            "optional": true,
            "running": true
        }
    ],
    "current_period_title": {
        "period": 2,
        "short_title": "2",
        "title": "2. Hälfte",
        "status_id": "period2",
        "can_end_game": true,
        "optional": false,
        "running": true
    },
    "arena": 336,
    "arena_name": "Schulzentrum Achter de Weiden",
    "arena_address": "Achter de Weiden 32, 22869 Schenefeld",
    "arena_short": "Schenefeld, Schulzentrum Achter de Weiden",
    "nominated_referees": "ABC",
    "deletable": false,
    "notice_type": "",
    "notice_string": "",
    "referees": [
        {
            "license_id": "6327",
            "first_name": "Ole",
            "last_name": "Keil"
        },
        {
            "license_id": "3147",
            "first_name": "Martin",
            "last_name": "Schlotfelds"
        }
    ]
}